encryptor3.py
setup.cfg
setup.py
encryptor3.egg-info/PKG-INFO
encryptor3.egg-info/SOURCES.txt
encryptor3.egg-info/dependency_links.txt
encryptor3.egg-info/entry_points.txt
encryptor3.egg-info/requires.txt
encryptor3.egg-info/top_level.txt