Metadata-Version: 1.0
Name: encryptor3
Version: 0.5
Summary: AWS File Encryptor
Home-page: https://github.com/jonwils24/encryptor3
Author: Jonathan Wilson
Author-email: wilsonwjonathan@gmail.com
License: UNKNOWN
Platform: UNKNOWN
